aspyre/__init__.py
aspyre/corpus_maker.py
aspyre/datamuse.py
aspyre/intent_target_analysis.py
aspyre/math.py
aspyre/oplsa.py
aspyre/scrap.py
aspyre/sutils.py
aspyre/term_stats.py
aspyre/term_stats_maker.py
aspyre/termstats.py
aspyre/text_processors.py
aspyre/wordnet_explorer.py
aspyre/words_api.py
aspyre/tests/__init__.py
aspyre/tests/termstats.py
aspyre-0.0.1.dist-info/LICENSE
aspyre-0.0.1.dist-info/METADATA
aspyre-0.0.1.dist-info/WHEEL
aspyre-0.0.1.dist-info/top_level.txt
aspyre-0.0.1.dist-info/RECORD
