Metadata-Version: 2.1
Name: aspyre
Version: 0.0.1
Summary: There's a bit of an air of mystery around this project...
Home-page: https://github.com/thorwhalen/ut/aspyre/aspyre
Author: thorwhalen
License: mit
Platform: any
